<map>
<bot id="7132">
      <name>Paul</name>
      <name langue="fr">Paul</name>
        <step type="fight" id="1">
		<start><![CDATA[Ready for the fight?]]></start>
		<win><![CDATA[You are so strong for me!]]></win>
		<monster id="Elowind" level="27" />
		<monster id="Elostorm" level="29" />
		<gain cash="300" />
	  </step>
    </bot>
<bot id="7033">
      <name>Antony</name>
      <name langue="fr">Antony</name>
        <step type="fight" id="1">
		<start><![CDATA[Ready for the fight?]]></start>
		<win><![CDATA[You are so strong for me!]]></win>
		<monster id="Polyrock" level="21" />
		<monster id="Polyrock" level="21" />
		<gain cash="200" />
	  </step>
    </bot>
</map>