<!-- default:
ratio_gender="50%"
catch_rate="100"
attack_level="1"
if level is 0, it's base attack
luck is in percent
evolution type can be: level (attribute level is the level), item (attribute level is the item id), trade (attribute level is useless)
-->
<monsters>
    <!-- ratio_gender: 0% only male, 100% only female, -1 no gender
    second line is stat at level 100-->
    <monster xp_max="500000" type="fire" pow="2" speed="130" attack="110" hp="200" catch_rate="100" id="1" weight="35kg" special_attack="120" defense="100" special_defense="100" ratio_gender="50%" give_sp="100" height="0.76m" egg_step="5000" give_xp="11000">
        <attack_list>
            <attack id="6" level="0"/>
            <attack id="5" level="0"/>
            <attack id="1" level="8"/>
            <attack id="9" level="14"/>
            <attack id="12" level="16"/>
            <attack id="1" level="20" attack_level="2"/>
            <attack id="9" level="36" attack_level="2"/>
        </attack_list>
        <drops>
            <drop item="2003" luck="20" quantity_min="1" quantity_max="3"/>
        </drops>
        <name>Panthera fira</name>
        <name lang="fr">Panthera fira</name>
        <description>Panthera fira is a very rare animal, it is characterized by its very hot skin..</description>
        <description lang="fr">Panthera fira est un animal très rare, il est caractérisé par sa peau très chaud..</description>
    </monster>
    <!-- ratio_gender: 0% only male, 100% only female, -1 no gender
    second line is stat at level 100-->
    <monster xp_max="400000" type="bird" pow="2" speed="120" attack="90" hp="190" catch_rate="100" id="2" weight="2kg" special_attack="80" defense="90" special_defense="80" ratio_gender="50%" give_sp="100" height="0.2m" egg_step="5000" give_xp="10000">
        <attack_list>
            <attack id="5" level="0"/>
            <attack id="7" level="0"/>
            <attack id="15" level="10"/>
            <attack id="15" level="18" attack_level="2"/>
        </attack_list>
        <evolutions>
            <evolution type="level" level="18" evolveTo="30"/>
        </evolutions>
        <drops>
            <drop item="1001" luck="2" quantity="1"/>
            <drop item="1002" luck="2" quantity="1"/>
            <drop item="1003" luck="2" quantity="1"/>
            <drop item="1004" luck="2" quantity="1"/>
            <drop item="1005" luck="2" quantity="1"/>
            <drop item="1006" luck="2" quantity="1"/>
            <drop item="1007" luck="2" quantity="1"/>
            <drop item="1008" luck="2" quantity="1"/>
            <drop item="1009" luck="2" quantity="1"/>
        </drops>
        <name>Elofly</name>
        <name lang="fr">Elofly</name>
        <description>Elofly frugivor is a small bird that lives in the forests and plains</description>
        <description lang="fr">Elofly est un petit oiseau frugivor qui vit dans les forêts et plaines</description>
    </monster>
    <monster xp_max="400000" type="plant" pow="2" speed="90" attack="150" hp="160" catch_rate="100" id="3" weight="15kg" special_attack="130" defense="90" special_defense="70" ratio_gender="50%" give_sp="100" height="0.54m" egg_step="5000" give_xp="10000">
        <attack_list>
            <attack id="6" level="0"/>
            <attack id="5" level="0"/>
            <attack id="3" level="8"/>
            <attack id="3" level="20" attack_level="2"/>
        </attack_list>
        <drops>
            <drop item="2014" luck="25" quantity="1"/>
        </drops>
        <name>Conileaf</name>
        <name lang="fr">Conifeuille</name>
        <description>Conileaf often confused with a fruit there remains a dangerous animal</description>
        <description lang="fr">Conifeuille souvent confondu avec un fruit il n'en reste un animal dangeureux</description>
    </monster>
    <monster xp_max="400000" type="psy" pow="2" speed="60" attack="50" hp="300" catch_rate="100" id="4" weight="23kg" special_attack="60" defense="120" special_defense="110" ratio_gender="50%" give_sp="100" height="0.54m" egg_step="5000" give_xp="10000">
        <attack_list>
            <attack id="5" level="0"/>
            <attack id="3" level="0"/>
            <attack id="16" level="0"/>
            <attack id="14" level="10"/>
            <attack id="14" level="18" attack_level="2"/>
            <attack id="12" level="22"/>
        </attack_list>
        <name>Tourbidi</name>
        <name lang="fr">Tourbidi</name>
        <description>Tourbidi is a very strange animal that spends its time turn on itself</description>
        <description lang="fr">Tourbidi est un animal très etrange qui passe son temps a tourner sur lui même </description>
    </monster>
    <monster xp_max="400000" type="stone;fight" pow="2" speed="30" attack="110" hp="190" catch_rate="100" id="5" weight="61kg" special_attack="80" defense="160" special_defense="70" ratio_gender="50%" give_sp="100" height="1.56m" egg_step="5000" give_xp="10000">
        <attack_list>
            <attack id="6" level="0"/>
            <attack id="5" level="0"/>
            <attack id="8" level="8"/>
            <attack id="8" level="20" attack_level="2"/>
        </attack_list>
        <drops>
            <drop item="2000" luck="20" quantity="1"/>
            <drop item="2001" luck="10" quantity="1"/>
            <drop item="2003" luck="30" quantity="1"/>
        </drops>
        <name>Polyrock</name>
        <name lang="fr">Polyrock</name>
        <description>Polyrock is mainly composed of stone, which makes it so resistant</description>
        <description lang="fr">Polyrock est composé principalement de pierre, ce qui le rend si résistant s</description>
    </monster>
    <monster xp_max="400000" type="water" pow="2" speed="100" attack="100" hp="200" catch_rate="100" id="6" weight="51kg" special_attack="80" defense="90" special_defense="80" ratio_gender="50%" give_sp="100" height="0.76m" egg_step="5000" give_xp="11000">
        <attack_list>
            <attack id="6" level="0"/>
            <attack id="5" level="0"/>
            <attack id="2" level="8"/>
            <attack id="12" level="16"/>
            <attack id="2" level="20" attack_level="2"/>
            <attack id="12" level="22" attack_level="2"/>
        </attack_list>
        <drops>
            <drop item="2010" luck="25" quantity="1"/>
        </drops>
        <name>Dinoflop</name>
        <name lang="fr">Dinoflop</name>
        <description>Dinoflop spends his life turning his back on his opponent, he is very playful cepandent</description>
        <description lang="fr">Dinoflop passe sa vie à tourner le dos à ses adversaire, il est cepandent très joueur</description>
    </monster>
    <monster xp_max="400000" type="normal" pow="2" speed="80" attack="120" hp="180" catch_rate="100" id="8" weight="34kg" special_attack="110" defense="130" special_defense="90" ratio_gender="50%" give_sp="100" height="0.76m" egg_step="5000" give_xp="11000">
        <attack_list>
            <attack id="6" level="0"/>
            <attack id="5" level="0"/>
            <attack id="2" level="8"/>
            <attack id="12" level="16"/>
            <attack id="2" level="20" attack_level="2"/>
        </attack_list>
        <name>Cochini</name>
        <name lang="fr">Cochini</name>
        <description>cochini</description>
        <description lang="fr">cochini</description>
    </monster>
    <monster xp_max="400000" type="water" pow="2" speed="80" attack="90" hp="200" catch_rate="100" id="9" weight="89kg" special_attack="100" defense="130" special_defense="120" ratio_gender="50%" give_sp="100" height="0.76m" egg_step="5000" give_xp="11000">
        <attack_list>
            <attack id="6" level="0"/>
            <attack id="5" level="0"/>
            <attack id="2" level="8"/>
        </attack_list>
        <name>Pharfan</name>
        <name lang="fr">Pharfan</name>
        <description>Pharfan is very rare, he enjoys watering the people they meet</description>
        <description lang="fr">Pharfan est très rare, il s'amuse arroser les gens qu'ils rencontre</description>
    </monster>
    <monster xp_max="400000" type="normal" pow="2" speed="150" attack="140" hp="180" catch_rate="100" id="13" weight="42kg" special_attack="110" defense="110" special_defense="100" ratio_gender="50%" give_sp="100" height="0.76m" egg_step="5000" give_xp="11000">
        <attack_list>
            <attack id="6" level="0"/>
            <attack id="5" level="0"/>
            <attack id="3" level="8"/>
            <attack id="12" level="12"/>
            <attack id="3" level="20" attack_level="2"/>
        </attack_list>
        <drops>
            <drop item="2012" luck="45" quantity="1"/>
        </drops>
        <evolutions>
            <evolution type="trade" evolveTo="14"/>
        </evolutions>
        <name>Sclairus</name>
        <name lang="fr">Sclairus</name>
        <description>Sclairus is an insect that feed exclusively.</description>
        <description lang="fr">Sclairus est un insecte qui se nourrir exclusivement</description>
    </monster>
    <monster xp_max="400000" type="normal;electric" pow="2" speed="140" attack="150" hp="220" catch_rate="100" id="14" weight="62kg" special_attack="130" defense="120" special_defense="110" ratio_gender="50%" give_sp="100" height="0.76m" egg_step="5000" give_xp="11000">
        <attack_list>
            <attack id="6" level="0"/>
            <attack id="5" level="0"/>
            <attack id="3" level="8"/>
            <attack id="12" level="12"/>
            <attack id="3" level="20" attack_level="2"/>
        </attack_list>
        <drops>
            <drop item="2012" luck="45" quantity="1"/>
        </drops>
        <name>Coleorus</name>
        <name lang="fr">Coléorus</name>
        <description>Coleorus is an insect that feed exclusively.</description>
        <description lang="fr">Coléorus est un insecte qui se nourrir exclusivement</description>
    </monster>
    <monster xp_max="400000" type="psy" pow="2" speed="120" attack="70" hp="190" catch_rate="100" id="17" weight="28kg" special_attack="230" defense="70" special_defense="130" ratio_gender="50%" give_sp="100" height="0.76m" egg_step="5000" give_xp="11000">
        <attack_list>
            <attack id="5" level="0"/>
            <attack id="7" level="0"/>
            <attack id="14" level="10"/>
            <attack id="4" level="16"/>
            <attack id="14" level="18" attack_level="2"/>
        </attack_list>
        <drops>
            <drop item="2004" luck="12" quantity_min="1" quantity_max="2"/>
        </drops>
        <name>Volcoli</name>
        <name lang="fr">Volcoli</name>
        <description>Volcoli is considered the forest nymph, she spent her life has protected the forest</description>
        <description lang="fr">Volcoli est considéré comme la nymphe des foret, elle passe sa vie a protégé la foret</description>
    </monster>
    <monster xp_max="400000" type="bird" pow="2" speed="110" attack="80" hp="200" catch_rate="100" id="18" weight="3kg" special_attack="60" defense="80" special_defense="80" ratio_gender="50%" give_sp="100" height="0.76m" egg_step="5000" give_xp="11000">
        <attack_list>
            <attack id="5" level="0"/>
            <attack id="7" level="0"/>
            <attack id="9" level="8"/>
            <attack id="15" level="10"/>
            <attack id="15" level="18" attack_level="2"/>
            <attack id="9" level="20" attack_level="2"/>
        </attack_list>
        <evolutions>
            <evolution type="level" level="26" evolveTo="32"/>
        </evolutions>
        <drops>
            <drop item="2002" luck="6" quantity="1"/>
            <drop item="2003" luck="18" quantity="1"/>
        </drops>
        <name>Noctula</name>
        <name lang="fr">Noctula</name>
        <description>Nocula small nocturnal bird, has a highly developed sense of hearing that allows him to what moves in total darkness.</description>
        <description lang="fr">Noctula petit oiseau nocturne, posséde un ouïe très développé qui lui permet de ce deplacé dans l'obscurité totale</description>
    </monster>
    <monster xp_max="400000" type="water" pow="2" speed="180" attack="200" hp="200" catch_rate="100" id="19" weight="14kg" special_attack="180" defense="250" special_defense="150" ratio_gender="50%" give_sp="100" height="0.76m" egg_step="5000" give_xp="11000">
        <attack_list>
            <attack id="5" level="0"/>
            <attack id="7" level="0"/>
            <attack id="2" level="8"/>
            <attack id="2" level="20" attack_level="2"/>
        </attack_list>
        <name>Rhinocarpe</name>
        <name lang="fr">Rhinocarpe</name>
        <description>Rhinocarpe is a marine animal that lives near the coast ca malgrés horn is a very friendly animal</description>
        <description lang="fr">Rhinocarpe est un animal marin, qui vit prés des cote malgrés ca corne c'est un animal très amical</description>
    </monster>
    <monster xp_max="400000" type="water" pow="2" speed="60" attack="90" hp="270" catch_rate="100" id="20" weight="28kg" special_attack="140" defense="80" special_defense="130" ratio_gender="50%" give_sp="100" height="0.76m" egg_step="5000" give_xp="11000">
        <attack_list>
            <attack id="5" level="0"/>
            <attack id="7" level="0"/>
            <attack id="2" level="8"/>
            <attack id="2" level="20" attack_level="2"/>
        </attack_list>
        <name>Hampotamos</name>
        <name lang="fr">Hampotamos</name>
        <description>Hampotamos Amphibian is an animal very awkward, it has the unfortunate tendency to fail everything</description>
        <description lang="fr">Hampotamos est un animal Amphibien très maladroit, il a la facheuse tendance à échouer tout ce qu'il entreprend</description>
    </monster>
    <monster xp_max="400000" type="fight" pow="2" speed="80" attack="160" hp="250" catch_rate="100" id="21" weight="23kg" special_attack="80" defense="110" special_defense="70" ratio_gender="50%" give_sp="100" height="0.76m" egg_step="5000" give_xp="11000">
        <attack_list>
            <attack id="5" level="0"/>
            <attack id="7" level="0"/>
            <attack id="2" level="8"/>
            <attack id="2" level="20" attack_level="2"/>
        </attack_list>
        <name>Urcine</name>
        <name lang="fr">Ursine</name>
        <description>Urcine is an aggressive animal, which does not consider the value of people in the affrontents with all that power, however it can reveal this very sociable</description>
        <description lang="fr">Urcine est un animal agressif, qui ne juge de la valeur des gens que en les affrontents avec toute ça force, malgrès les apparences il peut ce revelé très sociable</description>
    </monster>
    <monster xp_max="400000" type="poison" pow="2" speed="90" attack="50" hp="200" catch_rate="100" id="22" weight="3.4kg" special_attack="40" defense="80" special_defense="40" ratio_gender="50%" give_sp="100" height="0.76m" egg_step="5000" give_xp="11000">
        <attack_list>
            <attack id="5" level="0"/>
            <attack id="7" level="0"/>
            <attack id="9" level="8"/>
            <attack id="10" level="10"/>
            <attack id="9" level="20" attack_level="2"/>
            <attack id="10" level="22"/>
        </attack_list>
        <evolutions>
            <evolution type="level" level="26" evolveTo="23"/>
        </evolutions>
        <name>Chenipode</name>
        <name lang="fr">Chenipode</name>
        <description>Common wood's caterpillar, it has armor on the back to protect it from flying predators, she is very cuddly although toxic to who touch her</description>
        <description lang="fr">chenille des bois commune , elle possède une armure sur le dos pour la protéger des prédateurs volants, elle est très caline bien que toxique pour qui la touche</description>
    </monster>
    <monster xp_max="400000" type="poison" pow="2" speed="150" attack="80" hp="230" catch_rate="100" id="23" weight="12kg" special_attack="160" defense="110" special_defense="160" ratio_gender="50%" give_sp="100" height="0.76m" egg_step="5000" give_xp="11000">
        <attack_list>
            <attack id="5" level="0"/>
            <attack id="7" level="0"/>
            <attack id="9" level="8"/>
            <attack id="10" level="10"/>
            <attack id="9" level="20" attack_level="2"/>
            <attack id="10" level="22"/>
        </attack_list>
        <name>Exapode</name>
        <name lang="fr">Exapode</name>
        <description>Chrysalis of wood it has armor on almost integraliter body blocking him part her movements,, she is very cuddly although toxic to who touch her</description>
        <description lang="fr">Chrysalide des bois elle possède une armure sur la quasi integraliter du corps qui lui bloque en partie ses mouvements, elle est très caline bien que toxique pour qui la touche</description>
    </monster>
    <monster xp_max="400000" type="plant" pow="2" speed="110" attack="120" hp="225" catch_rate="100" id="25" weight="12kg" special_attack="100" defense="106" special_defense="70" ratio_gender="50%" give_sp="100" height="0.76m" egg_step="5000" give_xp="11000">
        <attack_list>
            <attack id="6" level="0"/>
            <attack id="5" level="0"/>
            <attack id="3" level="8"/>
            <attack id="3" level="20" attack_level="2"/>
        </attack_list>
        <name>Cowpignon</name>
        <name lang="fr">Cowpignon</name>
        <description>Cowpignon is an animal who have fun to challenge other monster.</description>
        <description lang="fr">Cowpignon est un animal qui s'amuse énormement à défier les autres monstre.</description>
    </monster>
    <monster xp_max="400000" type="plant" pow="2" speed="80" attack="75" hp="200" catch_rate="100" id="27" weight="12kg" special_attack="70" defense="126" special_defense="102" ratio_gender="50%" give_sp="100" height="0.76m" egg_step="5000" give_xp="11000">
        <attack_list>
            <attack id="6" level="0"/>
            <attack id="5" level="0"/>
            <attack id="3" level="8"/>
            <attack id="12" level="12"/>
            <attack id="3" level="20" attack_level="2"/>
            <attack id="12" level="22" attack_level="2"/>
        </attack_list>
        <name>Tarpeur</name>
        <name lang="fr">Tarpeur</name>
        <description>Tarpeur is a fearful animal, it lives hidden in a rock and hide at the slightest danger.</description>
        <description lang="fr">Tarpeur est un animal peureux, il vit caché dans un rocher et ce cache au moindre danger.</description>
    </monster>
    <monster xp_max="400000" type="bird" pow="2" speed="170" attack="130" hp="150" catch_rate="100" id="30" weight="2kg" special_attack="120" defense="120" special_defense="150" ratio_gender="50%" give_sp="100" height="0.2m" egg_step="5000" give_xp="10000">
        <attack_list>
            <attack id="5" level="0"/>
            <attack id="7" level="0"/>
            <attack id="15" level="10"/>
            <attack id="15" level="18" attack_level="2"/>
        </attack_list>
        <evolutions>
            <evolution type="level" level="38" evolveTo="31"/>
        </evolutions>
        <drops>
            <drop item="1001" luck="4" quantity="1"/>
            <drop item="1002" luck="4" quantity="1"/>
            <drop item="1003" luck="4" quantity="1"/>
            <drop item="1004" luck="4" quantity="1"/>
            <drop item="1005" luck="4" quantity="1"/>
            <drop item="1006" luck="4" quantity="1"/>
            <drop item="1007" luck="4" quantity="1"/>
            <drop item="1008" luck="4" quantity="1"/>
            <drop item="1009" luck="4" quantity="1"/>
        </drops>
        <name>Elowind</name>
        <name lang="fr">Elowind</name>
        <description>Elowind frugivor is a small bird that lives in the forests and plains</description>
        <description lang="fr">Elowind est un petit oiseau frugivor qui vit dans les forêts et plaines</description>
    </monster>
    <monster xp_max="400000" type="bird" pow="2" speed="200" attack="170" hp="175" catch_rate="100" id="31" weight="2kg" special_attack="160" defense="160" special_defense="200" ratio_gender="50%" give_sp="100" height="0.2m" egg_step="5000" give_xp="10000">
        <attack_list>
            <attack id="5" level="0"/>
            <attack id="7" level="0"/>
            <attack id="15" level="10"/>
            <attack id="15" level="18" attack_level="2"/>
        </attack_list>
        <drops>
            <drop item="1001" luck="6" quantity="1"/>
            <drop item="1002" luck="6" quantity="1"/>
            <drop item="1003" luck="6" quantity="1"/>
            <drop item="1004" luck="6" quantity="1"/>
            <drop item="1005" luck="6" quantity="1"/>
            <drop item="1006" luck="6" quantity="1"/>
            <drop item="1007" luck="6" quantity="1"/>
            <drop item="1008" luck="6" quantity="1"/>
            <drop item="1009" luck="6" quantity="1"/>
        </drops>
        <name>Elostorm</name>
        <name lang="fr">Elostorm</name>
        <description>Elostorm frugivor is a small bird that lives in the forests and plains</description>
        <description lang="fr">Elostorm est un petit oiseau frugivor qui vit dans les forêts et plaines</description>
    </monster>
    <monster xp_max="400000" type="bird" pow="2" speed="230" attack="170" hp="175" catch_rate="100" id="32" weight="2kg" special_attack="160" defense="150" special_defense="200" ratio_gender="50%" give_sp="100" height="0.2m" egg_step="5000" give_xp="10000">
        <attack_list>
            <attack id="5" level="0"/>
            <attack id="7" level="0"/>
            <attack id="15" level="10"/>
            <attack id="15" level="18" attack_level="2"/>
        </attack_list>
        <drops>
            <drop item="2002" luck="18" quantity="1"/>
            <drop item="2003" luck="54" quantity="1"/>
        </drops>
        <name>Noctalo</name>
        <name lang="fr">Noctalo</name>
        <description>Noctalo small nocturnal bird, has a highly developed sense of hearing that allows him to what moves in total darkness.</description>
        <description lang="fr">Noctalo petit oiseau nocturne, posséde un ouïe très développé qui lui permet de ce deplacé dans l'obscurité totale</description>
    </monster>
    <monster xp_max="400000" type="stone" pow="2" speed="110" attack="130" hp="150" catch_rate="100" id="33" weight="61kg" special_attack="120" defense="130" special_defense="80" ratio_gender="50%" give_sp="100" height="1.56m" egg_step="5000" give_xp="10000">
        <attack_list>
            <attack id="6" level="0"/>
            <attack id="5" level="0"/>
            <attack id="8" level="8"/>
            <attack id="8" level="20" attack_level="2"/>
        </attack_list>
        <evolutions>
            <evolution type="level" level="26" evolveTo="34"/>
        </evolutions>
        <drops>
            <drop item="2000" luck="20" quantity="1"/>
            <drop item="2001" luck="10" quantity="1"/>
            <drop item="2003" luck="30" quantity="1"/>
        </drops>
        <name>Selket</name>
        <name lang="fr">Selket</name>
        <description>Selket is mainly composed of stone, which makes it so resistant</description>
        <description lang="fr">Selket est composé principalement de pierre, ce qui le rend si résistant s</description>
    </monster>
<monster xp_max="400000" type="stone" pow="2" speed="130" attack="150" hp="160" catch_rate="100" id="34" weight="61kg" special_attack="140" defense="130" special_defense="100" ratio_gender="50%" give_sp="100" height="1.56m" egg_step="5000" give_xp="10000">
        <attack_list>
            <attack id="6" level="0"/>
            <attack id="5" level="0"/>
            <attack id="8" level="8"/>
            <attack id="8" level="20" attack_level="2"/>
        </attack_list>
        <drops>
            <drop item="2000" luck="20" quantity="1"/>
            <drop item="2001" luck="10" quantity="1"/>
            <drop item="2003" luck="30" quantity="1"/>
        </drops>
        <name>Selmatek</name>
        <name lang="fr">Selmatek</name>
        <description>Selket is mainly composed of stone, which makes it so resistant</description>
        <description lang="fr">Selket est composé principalement de pierre, ce qui le rend si résistant s</description>
    </monster>
    <monster xp_max="1600000" type="poison" pow="2" speed="110" attack="130" hp="150" catch_rate="20" id="36" weight="0.6kg" special_attack="120" defense="130" special_defense="80" ratio_gender="50%" give_sp="100" height="0.20m" egg_step="5000" give_xp="10000">
        <attack_list>
            <attack id="6" level="0"/>
            <attack id="5" level="0"/>
            <attack id="7" level="5"/>
            <attack id="10" level="8"/>
        </attack_list>
        <drops>
            <drop item="2000" luck="20" quantity="1"/>
            <drop item="2001" luck="10" quantity="1"/>
            <drop item="2003" luck="30" quantity="1"/>
        </drops>
        <evolutions>
            <evolution type="item" level="4010" evolveTo="41"/>
        </evolutions>
        <name>Snaki</name>
        <name lang="fr">Snaki</name>
        <description>Snaki is small hydre found into the hurge grass</description>
        <description lang="fr">Snaki est un petit hydre que l'ont trouve dans les grandes herbes</description>
    </monster>
    <monster xp_max="1600000" type="poison;fire" pow="2" speed="110" attack="130" hp="150" catch_rate="20" id="37" weight="0.6kg" special_attack="120" defense="130" special_defense="80" ratio_gender="50%" give_sp="100" height="0.20m" egg_step="5000" give_xp="10000">
        <attack_list>
            <attack id="6" level="0"/>
            <attack id="5" level="0"/>
            <attack id="7" level="5"/>
            <attack id="10" level="8"/>
            <attack id="17" byitem="17"/>
            <attack id="17" attack_level="2" byitem="18"/>
        </attack_list>
        <drops>
            <drop item="2000" luck="20" quantity="1"/>
            <drop item="2001" luck="10" quantity="1"/>
            <drop item="2003" luck="30" quantity="1"/>
        </drops>
        <name>Snokari</name>
        <name lang="fr">Snokari</name>
        <description>Snokari is hydre with dedoubled head due to alteration genetic</description>
        <description lang="fr">Snokari est unE hydre avec une double tête à cause d'une alteration génétique</description>
    </monster>
    <monster xp_max="1600000" type="normal" pow="2" speed="137" attack="112" hp="150" catch_rate="20" id="39" weight="0.6kg" special_attack="160" defense="120" special_defense="127" ratio_gender="50%" give_sp="100" height="0.20m" egg_step="5000" give_xp="10000">
        <attack_list>
            <attack id="6" level="0"/>
            <attack id="5" level="0"/>
            <attack id="7" level="5"/>
            <attack id="10" level="8"/>
            <attack id="17" byitem="17"/>
            <attack id="17" attack_level="2" byitem="18"/>
        </attack_list>
        <evolutions>
            <evolution type="level" level="26" evolveTo="34"/>
        </evolutions>
        <drops>
        </drops>
        <name>Vivipere</name>
        <name lang="fr">Vivipere</name>
        <description>Vivipere is a common snake encountered everywhere, who easily adapt</description>
        <description lang="fr">Vivipère est un serpent banal que l'on rencontre un peu partout avec de grande facilité à s'adapter</description>
    </monster>
    <monster xp_max="1600000" type="water" pow="2" speed="137" attack="112" hp="150" catch_rate="20" id="40" weight="0.6kg" special_attack="160" defense="120" special_defense="127" ratio_gender="50%" give_sp="100" height="0.20m" egg_step="5000" give_xp="10000">
        <attack_list>
            <attack id="5" level="0"/>
            <attack id="7" level="0"/>
            <attack id="2" level="8"/>
            <attack id="2" level="20" attack_level="2"/>
        </attack_list>
        <drops>
        </drops>
        <name>Vivisource</name>
        <name lang="fr">Vivisource</name>
        <description>Vivisource is a snake that lives in water, it kills its prey by drowning</description>
        <description lang="fr">Vivisource est un serpent qui vit dans l'eau, il tue ses proies en les noyant</description>
    </monster>
     <monster xp_max="400000" type="plant" pow="2" speed="90" attack="150" hp="160" catch_rate="100" id="41" weight="15kg" special_attack="130" defense="90" special_defense="70" ratio_gender="50%" give_sp="100" height="0.54m" egg_step="5000" give_xp="10000">
        <attack_list>
            <attack id="6" level="0"/>
            <attack id="5" level="0"/>
            <attack id="3" level="8"/>
            <attack id="3" level="20" attack_level="2"/>
        </attack_list>
        <drops>
        </drops>
        <name>Viviphyta</name>
        <name lang="fr">Viviphyta</name>
        <description>Viviphyta life in plants and tall trees, it only nourish this plant</description>
        <description lang="fr">Viviphyta vie dans les plantes et les grands arbres, il ce nourir exclusivement de végetaux</description>
    </monster>
    <monster xp_max="1600000" type="electric" pow="2" speed="132" attack="150" hp="150" catch_rate="20" id="42" weight="0.6kg" special_attack="180" defense="115" special_defense="115" ratio_gender="50%" give_sp="100" height="0.20m" egg_step="5000" give_xp="10000">
        <attack_list>
            <attack id="6" level="0"/>
            <attack id="5" level="0"/>
            <attack id="11" level="5"/>
            <attack id="10" level="8"/>
            <attack id="17" byitem="17"/>
            <attack id="17" attack_level="2" byitem="18"/>
        </attack_list>
        <drops>
        </drops>
        <name>Vivitron</name>
        <name lang="fr">Vivitron</name>
        <description>Vivitron is a snake that produces electricity for defense</description>
        <description lang="fr">Vivitron est un serpent qui produit de l'electricité pour se défendre</description>
    </monster>  



</monsters>
